[{"ANO_BO": "2019", "NUM_BO": "894", "NUMERO_BOLETIM": "894/2019", "BO_INICIADO": "02/04/2019 04:43", "BO_EMITIDO": "02/04/2019 07:43", "DATAOCORRENCIA": "02/04/2019", "PERIDOOCORRENCIA": "DE MADRUGADA", "DATACOMUNICACAO": "02/04/2019", "DATAELABORACAO": "02/04/2019 04:43", "BO_AUTORIA": "Desconhecida", "FLAGRANTE": "N\u00c6o", "NUMERO_BOLETIM_PRINCIPAL": "", "LOGRADOURO": "", "NUMERO": "0", "BAIRRO": "VILA S\u00c7O PAULO", "CIDADE": "ITANHAEM", "UF": "SP", "LATITUDE": "", "LONGITUDE": "", "DESCRICAOLOCAL": "Resid\u02c6ncia", "EXAME": "IC-IML", "SOLUCAO": "ENCAMINHAMENTO DP \u00b5REA DO FATO", "DELEGACIA_NOME": "DEL.SEC.ITANHAEM PLANT\u00c7O", "DELEGACIA_CIRCUNSCRICAO": "01\u00a7 D.P. ITANHAEM", "ESPECIE": "T\u00a1tulo II - Patrim\u201cnio (arts. 155 a 183)", "RUBRICA": "Roubo (art. 157) - RESIDENCIA", "DESDOBRAMENTO": "\u00f53o. Se da viol\u02c6ncia resulta morte:", "STATUS": "Consumado", "NOMEPESSOA": "AMYR ASSAID CUELLAR", "TIPOPESSOA": "V\u00a1tima", "VITIMAFATAL": "Sim", "RG": "6858241", "RG_UF": "SP", "NATURALIDADE": "GUAJARA-MIRIM -RO", "NACIONALIDADE": "BRASILEIRA", "SEXO": "Masculino", "DATANASCIMENTO": "17/02/1953", "IDADE": "66", "ESTADOCIVIL": "Casado", "PROFISSAO": "COMERCIANTE", "GRAUINSTRUCAO": "", "CORCUTIS": "Branca", "NATUREZAVINCULADA": "Roubo (art. 157)", "TIPOVINCULO": "V\u00a1tima", "RELACIONAMENTO": "", "PARENTESCO": "", "PLACA_VEICULO": "", "UF_VEICULO": "", "CIDADE_VEICULO": "", "DESCR_COR_VEICULO": "", "DESCR_MARCA_VEICULO": "", "ANO_FABRICACAO": "0", "ANO_MODELO": "0", "DESCR_TIPO_VEICULO": "", "QUANT_CELULAR": "", "MARCA_CELULAR": ""}, {"ANO_BO": "2019", "NUM_BO": "2219", "NUMERO_BOLETIM": "2219/2019", "BO_INICIADO": "04/04/2019 16:02", "BO_EMITIDO": "04/04/2019 17:10", "DATAOCORRENCIA": "04/04/2019", "PERIDOOCORRENCIA": "A TARDE", "DATACOMUNICACAO": "04/04/2019", "DATAELABORACAO": "04/04/2019 16:02", "BO_AUTORIA": "Desconhecida", "FLAGRANTE": "N\u00c6o", "NUMERO_BOLETIM_PRINCIPAL": "", "LOGRADOURO": "", "NUMERO": "0", "BAIRRO": "JARDIM SAO CRISPIN", "CIDADE": "JAU", "UF": "SP", "LATITUDE": "", "LONGITUDE": "", "DESCRICAOLOCAL": "Resid\u02c6ncia", "EXAME": "IML", "SOLUCAO": "ENCAMINHAMENTO DP \u00b5REA DO FATO", "DELEGACIA_NOME": "CENTRAL POL.JUD-JA\u00e9", "DELEGACIA_CIRCUNSCRICAO": "02\u00a7 D.P. JA\u00e9", "ESPECIE": "T\u00a1tulo II - Patrim\u201cnio (arts. 155 a 183)", "RUBRICA": "Roubo (art. 157) - RESIDENCIA", "DESDOBRAMENTO": "\u00f53o. Se da viol\u02c6ncia resulta morte:", "STATUS": "Consumado", "NOMEPESSOA": "MANOEL APARECIDO GARCIA", "TIPOPESSOA": "V\u00a1tima", "VITIMAFATAL": "Sim", "RG": "12910568", "RG_UF": "SP", "NATURALIDADE": "MINEIROS DO TIETE", "NACIONALIDADE": "BRASILEIRA", "SEXO": "Masculino", "DATANASCIMENTO": "26/03/1957", "IDADE": "62", "ESTADOCIVIL": "Solteiro", "PROFISSAO": "CALCADISTA", "GRAUINSTRUCAO": "", "CORCUTIS": "Branca", "NATUREZAVINCULADA": "Roubo (art. 157)", "TIPOVINCULO": "V\u00a1tima", "RELACIONAMENTO": "", "PARENTESCO": "", "PLACA_VEICULO": "", "UF_VEICULO": "", "CIDADE_VEICULO": "", "DESCR_COR_VEICULO": "", "DESCR_MARCA_VEICULO": "", "ANO_FABRICACAO": "0", "ANO_MODELO": "0", "DESCR_TIPO_VEICULO": "", "QUANT_CELULAR": "", "MARCA_CELULAR": ""}, {"ANO_BO": "2019", "NUM_BO": "1063", "NUMERO_BOLETIM": "1063/2019", "BO_INICIADO": "05/04/2019 11:43", "BO_EMITIDO": "05/04/2019 13:24", "DATAOCORRENCIA": "04/04/2019", "PERIDOOCORRENCIA": "A NOITE", "DATACOMUNICACAO": "05/04/2019", "DATAELABORACAO": "05/04/2019 11:43", "BO_AUTORIA": "Desconhecida", "FLAGRANTE": "N\u00c6o", "NUMERO_BOLETIM_PRINCIPAL": "1061/2019 - 120609", "LOGRADOURO": "RUA VIT\u00e0RIA DANTE DE CAMARGO", "NUMERO": "133", "BAIRRO": "RURAL", "CIDADE": "TATUI", "UF": "SP", "LATITUDE": "-23,34328558", "LONGITUDE": "-47,82589433", "DESCRICAOLOCAL": "Via p\u00a3blica", "EXAME": "IML", "SOLUCAO": "BO PARA ADENDO", "DELEGACIA_NOME": "DEL.POL.PLANT\u00c7O TATUI", "DELEGACIA_CIRCUNSCRICAO": "DEL.POL.TATUI", "ESPECIE": "T\u00a1tulo II - Patrim\u201cnio (arts. 155 a 183)", "RUBRICA": "Roubo (art. 157) - VEICULO", "DESDOBRAMENTO": "\u00f53o. Se da viol\u02c6ncia resulta morte:", "STATUS": "Consumado", "NOMEPESSOA": "EDER DIEGO BAPTISTA DE CAMARGO", "TIPOPESSOA": "V\u00a1tima", "VITIMAFATAL": "Sim", "RG": "42561284", "RG_UF": "SP", "NATURALIDADE": "TATU\u00d6-SP", "NACIONALIDADE": "BRASILEIRA", "SEXO": "Masculino", "DATANASCIMENTO": "", "IDADE": "", "ESTADOCIVIL": "Solteiro", "PROFISSAO": "FUNCION.PUBLICO MUNICIPAL", "GRAUINSTRUCAO": "2 Grau completo", "CORCUTIS": "Branca", "NATUREZAVINCULADA": "Roubo (art. 157)", "TIPOVINCULO": "V\u00a1tima", "RELACIONAMENTO": "", "PARENTESCO": "", "PLACA_VEICULO": "ECA1358", "UF_VEICULO": "SP", "CIDADE_VEICULO": "TATUI", "DESCR_COR_VEICULO": "Vermelho", "DESCR_MARCA_VEICULO": "HONDA/BIZ 125 ES", "ANO_FABRICACAO": "2008", "ANO_MODELO": "2008", "DESCR_TIPO_VEICULO": "MOTONETA", "QUANT_CELULAR": "", "MARCA_CELULAR": ""}, {"ANO_BO": "2019", "NUM_BO": "2013", "NUMERO_BOLETIM": "2013/2019", "BO_INICIADO": "05/04/2019 14:32", "BO_EMITIDO": "05/04/2019 18:46", "DATAOCORRENCIA": "05/04/2019", "PERIDOOCORRENCIA": "A TARDE", "DATACOMUNICACAO": "05/04/2019", "DATAELABORACAO": "05/04/2019 14:32", "BO_AUTORIA": "Desconhecida", "FLAGRANTE": "N\u00c6o", "NUMERO_BOLETIM_PRINCIPAL": "1969/2019 - 10335", "LOGRADOURO": "", "NUMERO": "0", "BAIRRO": "BRASILANDIA", "CIDADE": "S.PAULO", "UF": "SP", "LATITUDE": "", "LONGITUDE": "", "DESCRICAOLOCAL": "Resid\u02c6ncia", "EXAME": "IML", "SOLUCAO": "BO PARA ADENDO", "DELEGACIA_NOME": "72\u00a7 D.P. VILA PENTEADO", "DELEGACIA_CIRCUNSCRICAO": "72\u00a7 D.P. VILA PENTEADO", "ESPECIE": "T\u00a1tulo II - Patrim\u201cnio (arts. 155 a 183)", "RUBRICA": "Roubo (art. 157) - TRANSEUNTE", "DESDOBRAMENTO": "\u00f53o. Se da viol\u02c6ncia resulta morte:", "STATUS": "Consumado", "NOMEPESSOA": "JORGE SANTA BARBARA", "TIPOPESSOA": "V\u00a1tima", "VITIMAFATAL": "Sim", "RG": "13779714", "RG_UF": "SP", "NATURALIDADE": "S.PAULO -SP", "NACIONALIDADE": "BRASILEIRA", "SEXO": "Masculino", "DATANASCIMENTO": "04/07/1963", "IDADE": "55", "ESTADOCIVIL": "Solteiro", "PROFISSAO": "AJUDANTE DE MOTORISTA", "GRAUINSTRUCAO": "", "CORCUTIS": "Parda", "NATUREZAVINCULADA": "Roubo (art. 157)", "TIPOVINCULO": "V\u00a1tima", "RELACIONAMENTO": "", "PARENTESCO": "", "PLACA_VEICULO": "", "UF_VEICULO": "", "CIDADE_VEICULO": "", "DESCR_COR_VEICULO": "", "DESCR_MARCA_VEICULO": "", "ANO_FABRICACAO": "0", "ANO_MODELO": "0", "DESCR_TIPO_VEICULO": "", "QUANT_CELULAR": "", "MARCA_CELULAR": ""}, {"ANO_BO": "2019", "NUM_BO": "2264", "NUMERO_BOLETIM": "2264/2019", "BO_INICIADO": "06/04/2019 13:46", "BO_EMITIDO": "06/04/2019 19:28", "DATAOCORRENCIA": "06/04/2019", "PERIDOOCORRENCIA": "PELA MANH\u00c7", "DATACOMUNICACAO": "06/04/2019", "DATAELABORACAO": "06/04/2019 13:46", "BO_AUTORIA": "Desconhecida", "FLAGRANTE": "N\u00c6o", "NUMERO_BOLETIM_PRINCIPAL": "", "LOGRADOURO": "RUA ANT\u00e2NINA DO NORTE", "NUMERO": "100", "BAIRRO": "PIMENTAS", "CIDADE": "GUARULHOS", "UF": "SP", "LATITUDE": "-23,44914345", "LONGITUDE": "-46,40475924", "DESCRICAOLOCAL": "Via p\u00a3blica", "EXAME": "IC-IML", "SOLUCAO": "APRECIA\u20ac\u00c7O DO DELEGADO TITULAR", "DELEGACIA_NOME": "04\u00a7 D.P. GUARULHOS", "DELEGACIA_CIRCUNSCRICAO": "04\u00a7 D.P. GUARULHOS", "ESPECIE": "T\u00a1tulo II - Patrim\u201cnio (arts. 155 a 183)", "RUBRICA": "Roubo (art. 157) - OUTROS", "DESDOBRAMENTO": "\u00f53o. Se da viol\u02c6ncia resulta morte:", "STATUS": "Consumado", "NOMEPESSOA": "WLADIMIR NUNES DOS SANTOS", "TIPOPESSOA": "V\u00a1tima", "VITIMAFATAL": "Sim", "RG": "35960343", "RG_UF": "SP", "NATURALIDADE": "SOROCABA -SP", "NACIONALIDADE": "BRASILEIRA", "SEXO": "Masculino", "DATANASCIMENTO": "07/12/1983", "IDADE": "35", "ESTADOCIVIL": "Casado", "PROFISSAO": "AUTONOMO(A)", "GRAUINSTRUCAO": "", "CORCUTIS": "Branca", "NATUREZAVINCULADA": "Roubo (art. 157)", "TIPOVINCULO": "V\u00a1tima", "RELACIONAMENTO": "", "PARENTESCO": "", "PLACA_VEICULO": "", "UF_VEICULO": "", "CIDADE_VEICULO": "", "DESCR_COR_VEICULO": "", "DESCR_MARCA_VEICULO": "", "ANO_FABRICACAO": "0", "ANO_MODELO": "0", "DESCR_TIPO_VEICULO": "", "QUANT_CELULAR": "", "MARCA_CELULAR": ""}, {"ANO_BO": "2019", "NUM_BO": "815", "NUMERO_BOLETIM": "815/2019", "BO_INICIADO": "11/04/2019 10:11", "BO_EMITIDO": "11/04/2019 10:23", "DATAOCORRENCIA": "29/06/2015", "PERIDOOCORRENCIA": "A NOITE", "DATACOMUNICACAO": "11/04/2019", "DATAELABORACAO": "11/04/2019 10:11", "BO_AUTORIA": "Desconhecida", "FLAGRANTE": "N\u00c6o", "NUMERO_BOLETIM_PRINCIPAL": "2111/2015 - 70928", "LOGRADOURO": "RUA BELO HORIZONTE", "NUMERO": "279", "BAIRRO": "RESIDENCIAL SAO LUIZ", "CIDADE": "HORTOLANDIA", "UF": "SP", "LATITUDE": "-22,89921326", "LONGITUDE": "-47,19645046", "DESCRICAOLOCAL": "Restaurante e afins", "EXAME": "IC-IML", "SOLUCAO": "BO PARA ADENDO", "DELEGACIA_NOME": "02\u00a7 D.P. HORTOL\u00b6NDIA", "DELEGACIA_CIRCUNSCRICAO": "02\u00a7 D.P. HORTOL\u00b6NDIA", "ESPECIE": "T\u00a1tulo II - Patrim\u201cnio (arts. 155 a 183)", "RUBRICA": "Roubo (art. 157) - ESTABELECIMENTO COMERCIAL", "DESDOBRAMENTO": "\u00f53o. Se da viol\u02c6ncia resulta morte:", "STATUS": "Consumado", "NOMEPESSOA": "HENRIQUE DOS SANTOS FERRAZ", "TIPOPESSOA": "V\u00a1tima", "VITIMAFATAL": "Sim", "RG": "44266016", "RG_UF": "SP", "NATURALIDADE": "CAMPINAS -SP", "NACIONALIDADE": "BRASILEIRA", "SEXO": "Masculino", "DATANASCIMENTO": "25/09/1988", "IDADE": "26", "ESTADOCIVIL": "Solteiro", "PROFISSAO": "INSTALADOR(A)", "GRAUINSTRUCAO": "2 Grau completo", "CORCUTIS": "Branca", "NATUREZAVINCULADA": "Roubo (art. 157)", "TIPOVINCULO": "V\u00a1tima", "RELACIONAMENTO": "", "PARENTESCO": "", "PLACA_VEICULO": "", "UF_VEICULO": "", "CIDADE_VEICULO": "", "DESCR_COR_VEICULO": "", "DESCR_MARCA_VEICULO": "", "ANO_FABRICACAO": "0", "ANO_MODELO": "0", "DESCR_TIPO_VEICULO": "", "QUANT_CELULAR": "", "MARCA_CELULAR": ""}, {"ANO_BO": "2019", "NUM_BO": "815", "NUMERO_BOLETIM": "815/2019", "BO_INICIADO": "11/04/2019 10:11", "BO_EMITIDO": "11/04/2019 10:23", "DATAOCORRENCIA": "29/06/2015", "PERIDOOCORRENCIA": "A NOITE", "DATACOMUNICACAO": "11/04/2019", "DATAELABORACAO": "11/04/2019 10:11", "BO_AUTORIA": "Desconhecida", "FLAGRANTE": "N\u00c6o", "NUMERO_BOLETIM_PRINCIPAL": "2111/2015 - 70928", "LOGRADOURO": "RUA BELO HORIZONTE", "NUMERO": "279", "BAIRRO": "RESIDENCIAL SAO LUIZ", "CIDADE": "HORTOLANDIA", "UF": "SP", "LATITUDE": "-22,89921326", "LONGITUDE": "-47,19645046", "DESCRICAOLOCAL": "Restaurante e afins", "EXAME": "IC-IML", "SOLUCAO": "BO PARA ADENDO", "DELEGACIA_NOME": "02\u00a7 D.P. HORTOL\u00b6NDIA", "DELEGACIA_CIRCUNSCRICAO": "02\u00a7 D.P. HORTOL\u00b6NDIA", "ESPECIE": "Localiza\u2021\u00c6o e/ou Devolu\u2021\u00c6o", "RUBRICA": "Localiza\u2021\u00c6o/Apreens\u00c6o de ve\u00a1culo", "DESDOBRAMENTO": "", "STATUS": "Consumado", "NOMEPESSOA": "", "TIPOPESSOA": "", "VITIMAFATAL": "", "RG": "", "RG_UF": "", "NATURALIDADE": "", "NACIONALIDADE": "", "SEXO": "", "DATANASCIMENTO": "", "IDADE": "", "ESTADOCIVIL": "", "PROFISSAO": "", "GRAUINSTRUCAO": "", "CORCUTIS": "", "NATUREZAVINCULADA": "", "TIPOVINCULO": "", "RELACIONAMENTO": "", "PARENTESCO": "", "PLACA_VEICULO": "BIM0679", "UF_VEICULO": "SP", "CIDADE_VEICULO": "HORTOLANDIA", "DESCR_COR_VEICULO": "Branco", "DESCR_MARCA_VEICULO": "VW/GOL CL 1.8", "ANO_FABRICACAO": "1991", "ANO_MODELO": "1992", "DESCR_TIPO_VEICULO": "AUTOMOVEL", "QUANT_CELULAR": "", "MARCA_CELULAR": ""}, {"ANO_BO": "2019", "NUM_BO": "815", "NUMERO_BOLETIM": "815/2019", "BO_INICIADO": "11/04/2019 10:11", "BO_EMITIDO": "11/04/2019 10:23", "DATAOCORRENCIA": "29/06/2015", "PERIDOOCORRENCIA": "A NOITE", "DATACOMUNICACAO": "11/04/2019", "DATAELABORACAO": "11/04/2019 10:11", "BO_AUTORIA": "Desconhecida", "FLAGRANTE": "N\u00c6o", "NUMERO_BOLETIM_PRINCIPAL": "2111/2015 - 70928", "LOGRADOURO": "RUA BELO HORIZONTE", "NUMERO": "279", "BAIRRO": "RESIDENCIAL SAO LUIZ", "CIDADE": "HORTOLANDIA", "UF": "SP", "LATITUDE": "-22,89921326", "LONGITUDE": "-47,19645046", "DESCRICAOLOCAL": "Restaurante e afins", "EXAME": "IC-IML", "SOLUCAO": "BO PARA ADENDO", "DELEGACIA_NOME": "02\u00a7 D.P. HORTOL\u00b6NDIA", "DELEGACIA_CIRCUNSCRICAO": "02\u00a7 D.P. HORTOL\u00b6NDIA", "ESPECIE": "T\u00a1tulo II - Patrim\u201cnio (arts. 155 a 183)", "RUBRICA": "Roubo (art. 157) - ESTABELECIMENTO COMERCIAL", "DESDOBRAMENTO": "\u00f53o. Se da viol\u02c6ncia resulta morte:", "STATUS": "Consumado", "NOMEPESSOA": "HENRIQUE DOS SANTOS FERRAZ", "TIPOPESSOA": "V\u00a1tima", "VITIMAFATAL": "Sim", "RG": "44266016", "RG_UF": "SP", "NATURALIDADE": "CAMPINAS -SP", "NACIONALIDADE": "BRASILEIRA", "SEXO": "Masculino", "DATANASCIMENTO": "25/09/1988", "IDADE": "26", "ESTADOCIVIL": "Solteiro", "PROFISSAO": "INSTALADOR(A)", "GRAUINSTRUCAO": "2 Grau completo", "CORCUTIS": "Branca", "NATUREZAVINCULADA": "Roubo (art. 157)", "TIPOVINCULO": "V\u00a1tima", "RELACIONAMENTO": "", "PARENTESCO": "", "PLACA_VEICULO": "BIM0679", "UF_VEICULO": "SP", "CIDADE_VEICULO": "HORTOLANDIA", "DESCR_COR_VEICULO": "Branco", "DESCR_MARCA_VEICULO": "VW/GOL CL 1.8", "ANO_FABRICACAO": "1991", "ANO_MODELO": "1992", "DESCR_TIPO_VEICULO": "AUTOMOVEL", "QUANT_CELULAR": "", "MARCA_CELULAR": ""}, {"ANO_BO": "2019", "NUM_BO": "815", "NUMERO_BOLETIM": "815/2019", "BO_INICIADO": "11/04/2019 10:11", "BO_EMITIDO": "11/04/2019 10:23", "DATAOCORRENCIA": "29/06/2015", "PERIDOOCORRENCIA": "A NOITE", "DATACOMUNICACAO": "11/04/2019", "DATAELABORACAO": "11/04/2019 10:11", "BO_AUTORIA": "Desconhecida", "FLAGRANTE": "N\u00c6o", "NUMERO_BOLETIM_PRINCIPAL": "2111/2015 - 70928", "LOGRADOURO": "RUA BELO HORIZONTE", "NUMERO": "279", "BAIRRO": "RESIDENCIAL SAO LUIZ", "CIDADE": "HORTOLANDIA", "UF": "SP", "LATITUDE": "-22,89921326", "LONGITUDE": "-47,19645046", "DESCRICAOLOCAL": "Restaurante e afins", "EXAME": "IC-IML", "SOLUCAO": "BO PARA ADENDO", "DELEGACIA_NOME": "02\u00a7 D.P. HORTOL\u00b6NDIA", "DELEGACIA_CIRCUNSCRICAO": "02\u00a7 D.P. HORTOL\u00b6NDIA", "ESPECIE": "T\u00a1tulo II - Patrim\u201cnio (arts. 155 a 183)", "RUBRICA": "Roubo (art. 157) - VEICULO", "DESDOBRAMENTO": "", "STATUS": "Consumado", "NOMEPESSOA": "HENRIQUE DOS SANTOS FERRAZ", "TIPOPESSOA": "V\u00a1tima", "VITIMAFATAL": "Sim", "RG": "44266016", "RG_UF": "SP", "NATURALIDADE": "CAMPINAS -SP", "NACIONALIDADE": "BRASILEIRA", "SEXO": "Masculino", "DATANASCIMENTO": "25/09/1988", "IDADE": "26", "ESTADOCIVIL": "Solteiro", "PROFISSAO": "INSTALADOR(A)", "GRAUINSTRUCAO": "2 Grau completo", "CORCUTIS": "Branca", "NATUREZAVINCULADA": "Roubo (art. 157)", "TIPOVINCULO": "V\u00a1tima", "RELACIONAMENTO": "", "PARENTESCO": "", "PLACA_VEICULO": "", "UF_VEICULO": "", "CIDADE_VEICULO": "", "DESCR_COR_VEICULO": "", "DESCR_MARCA_VEICULO": "", "ANO_FABRICACAO": "0", "ANO_MODELO": "0", "DESCR_TIPO_VEICULO": "", "QUANT_CELULAR": "", "MARCA_CELULAR": ""}, {"ANO_BO": "2019", "NUM_BO": "815", "NUMERO_BOLETIM": "815/2019", "BO_INICIADO": "11/04/2019 10:11", "BO_EMITIDO": "11/04/2019 10:23", "DATAOCORRENCIA": "29/06/2015", "PERIDOOCORRENCIA": "A NOITE", "DATACOMUNICACAO": "11/04/2019", "DATAELABORACAO": "11/04/2019 10:11", "BO_AUTORIA": "Desconhecida", "FLAGRANTE": "N\u00c6o", "NUMERO_BOLETIM_PRINCIPAL": "2111/2015 - 70928", "LOGRADOURO": "RUA BELO HORIZONTE", "NUMERO": "279", "BAIRRO": "RESIDENCIAL SAO LUIZ", "CIDADE": "HORTOLANDIA", "UF": "SP", "LATITUDE": "-22,89921326", "LONGITUDE": "-47,19645046", "DESCRICAOLOCAL": "Restaurante e afins", "EXAME": "IC-IML", "SOLUCAO": "BO PARA ADENDO", "DELEGACIA_NOME": "02\u00a7 D.P. HORTOL\u00b6NDIA", "DELEGACIA_CIRCUNSCRICAO": "02\u00a7 D.P. HORTOL\u00b6NDIA", "ESPECIE": "Localiza\u2021\u00c6o e/ou Devolu\u2021\u00c6o", "RUBRICA": "Localiza\u2021\u00c6o/Apreens\u00c6o de ve\u00a1culo", "DESDOBRAMENTO": "", "STATUS": "Consumado", "NOMEPESSOA": "", "TIPOPESSOA": "", "VITIMAFATAL": "", "RG": "", "RG_UF": "", "NATURALIDADE": "", "NACIONALIDADE": "", "SEXO": "", "DATANASCIMENTO": "", "IDADE": "", "ESTADOCIVIL": "", "PROFISSAO": "", "GRAUINSTRUCAO": "", "CORCUTIS": "", "NATUREZAVINCULADA": "", "TIPOVINCULO": "", "RELACIONAMENTO": "", "PARENTESCO": "", "PLACA_VEICULO": "", "UF_VEICULO": "", "CIDADE_VEICULO": "", "DESCR_COR_VEICULO": "", "DESCR_MARCA_VEICULO": "", "ANO_FABRICACAO": "0", "ANO_MODELO": "0", "DESCR_TIPO_VEICULO": "", "QUANT_CELULAR": "", "MARCA_CELULAR": ""}, {"ANO_BO": "2019", "NUM_BO": "815", "NUMERO_BOLETIM": "815/2019", "BO_INICIADO": "11/04/2019 10:11", "BO_EMITIDO": "11/04/2019 10:23", "DATAOCORRENCIA": "29/06/2015", "PERIDOOCORRENCIA": "A NOITE", "DATACOMUNICACAO": "11/04/2019", "DATAELABORACAO": "11/04/2019 10:11", "BO_AUTORIA": "Desconhecida", "FLAGRANTE": "N\u00c6o", "NUMERO_BOLETIM_PRINCIPAL": "2111/2015 - 70928", "LOGRADOURO": "RUA BELO HORIZONTE", "NUMERO": "279", "BAIRRO": "RESIDENCIAL SAO LUIZ", "CIDADE": "HORTOLANDIA", "UF": "SP", "LATITUDE": "-22,89921326", "LONGITUDE": "-47,19645046", "DESCRICAOLOCAL": "Restaurante e afins", "EXAME": "IC-IML", "SOLUCAO": "BO PARA ADENDO", "DELEGACIA_NOME": "02\u00a7 D.P. HORTOL\u00b6NDIA", "DELEGACIA_CIRCUNSCRICAO": "02\u00a7 D.P. HORTOL\u00b6NDIA", "ESPECIE": "T\u00a1tulo II - Patrim\u201cnio (arts. 155 a 183)", "RUBRICA": "Roubo (art. 157) - VEICULO", "DESDOBRAMENTO": "", "STATUS": "Consumado", "NOMEPESSOA": "HENRIQUE DOS SANTOS FERRAZ", "TIPOPESSOA": "V\u00a1tima", "VITIMAFATAL": "Sim", "RG": "44266016", "RG_UF": "SP", "NATURALIDADE": "CAMPINAS -SP", "NACIONALIDADE": "BRASILEIRA", "SEXO": "Masculino", "DATANASCIMENTO": "25/09/1988", "IDADE": "26", "ESTADOCIVIL": "Solteiro", "PROFISSAO": "INSTALADOR(A)", "GRAUINSTRUCAO": "2 Grau completo", "CORCUTIS": "Branca", "NATUREZAVINCULADA": "Roubo (art. 157)", "TIPOVINCULO": "V\u00a1tima", "RELACIONAMENTO": "", "PARENTESCO": "", "PLACA_VEICULO": "BIM0679", "UF_VEICULO": "SP", "CIDADE_VEICULO": "HORTOLANDIA", "DESCR_COR_VEICULO": "Branco", "DESCR_MARCA_VEICULO": "VW/GOL CL 1.8", "ANO_FABRICACAO": "1991", "ANO_MODELO": "1992", "DESCR_TIPO_VEICULO": "AUTOMOVEL", "QUANT_CELULAR": "", "MARCA_CELULAR": ""}, {"ANO_BO": "2019", "NUM_BO": "1354", "NUMERO_BOLETIM": "1354/2019", "BO_INICIADO": "12/04/2019 00:52", "BO_EMITIDO": "12/04/2019 05:31", "DATAOCORRENCIA": "11/04/2019", "PERIDOOCORRENCIA": "A NOITE", "DATACOMUNICACAO": "12/04/2019", "DATAELABORACAO": "12/04/2019 00:52", "BO_AUTORIA": "Conhecida", "FLAGRANTE": "Sim", "NUMERO_BOLETIM_PRINCIPAL": "", "LOGRADOURO": "RUA XINGU", "NUMERO": "593", "BAIRRO": "VILA MARIANA", "CIDADE": "FERRAZ DE VASCONCELOS", "UF": "SP", "LATITUDE": "-23,55046321", "LONGITUDE": "-46,39322622", "DESCRICAOLOCAL": "Via p\u00a3blica", "EXAME": "IC-IML", "SOLUCAO": "BO PARA FLAGRANTE", "DELEGACIA_NOME": "DEL.POL.FERRAZ DE VASCONCELOS", "DELEGACIA_CIRCUNSCRICAO": "DEL.POL.FERRAZ DE VASCONCELOS", "ESPECIE": "T\u00a1tulo II - Patrim\u201cnio (arts. 155 a 183)", "RUBRICA": "Roubo (art. 157) - TRANSEUNTE", "DESDOBRAMENTO": "\u00f53o. Se da viol\u02c6ncia resulta morte:", "STATUS": "Consumado", "NOMEPESSOA": "CLEBER DOS SANTOS DONARIO", "TIPOPESSOA": "V\u00a1tima", "VITIMAFATAL": "Sim", "RG": "32682676", "RG_UF": "SP", "NATURALIDADE": "S.PAULO -SP", "NACIONALIDADE": "BRASILEIRA", "SEXO": "Masculino", "DATANASCIMENTO": "15/09/1984", "IDADE": "34", "ESTADOCIVIL": "Solteiro", "PROFISSAO": "VENDEDOR(A)", "GRAUINSTRUCAO": "", "CORCUTIS": "Branca", "NATUREZAVINCULADA": "Roubo (art. 157)", "TIPOVINCULO": "V\u00a1tima", "RELACIONAMENTO": "", "PARENTESCO": "", "PLACA_VEICULO": "", "UF_VEICULO": "", "CIDADE_VEICULO": "", "DESCR_COR_VEICULO": "", "DESCR_MARCA_VEICULO": "", "ANO_FABRICACAO": "0", "ANO_MODELO": "0", "DESCR_TIPO_VEICULO": "", "QUANT_CELULAR": "", "MARCA_CELULAR": ""}, {"ANO_BO": "2019", "NUM_BO": "2592", "NUMERO_BOLETIM": "2592/2019", "BO_INICIADO": "16/04/2019 09:14", "BO_EMITIDO": "16/04/2019 09:26", "DATAOCORRENCIA": "15/04/2019", "PERIDOOCORRENCIA": "A NOITE", "DATACOMUNICACAO": "16/04/2019", "DATAELABORACAO": "16/04/2019 09:14", "BO_AUTORIA": "Desconhecida", "FLAGRANTE": "N\u00c6o", "NUMERO_BOLETIM_PRINCIPAL": "2588/2019 - 10226", "LOGRADOURO": "", "NUMERO": "0", "BAIRRO": "JARDIM COLINA", "CIDADE": "S.PAULO", "UF": "SP", "LATITUDE": "", "LONGITUDE": "", "DESCRICAOLOCAL": "Resid\u02c6ncia", "EXAME": "", "SOLUCAO": "BO PARA ADENDO", "DELEGACIA_NOME": "26\u00a7 D.P. SACOMA", "DELEGACIA_CIRCUNSCRICAO": "26\u00a7 D.P. SACOMA", "ESPECIE": "T\u00a1tulo II - Patrim\u201cnio (arts. 155 a 183)", "RUBRICA": "Roubo (art. 157) - RESIDENCIA", "DESDOBRAMENTO": "\u00f53o. Se da viol\u02c6ncia resulta morte:", "STATUS": "Consumado", "NOMEPESSOA": "MASAAKI HAYAMA", "TIPOPESSOA": "V\u00a1tima", "VITIMAFATAL": "Sim", "RG": "", "RG_UF": "SP", "NATURALIDADE": "JAPAO", "NACIONALIDADE": "JAPAO", "SEXO": "Masculino", "DATANASCIMENTO": "06/02/1952", "IDADE": "67", "ESTADOCIVIL": "Casado", "PROFISSAO": "", "GRAUINSTRUCAO": "Superior completo", "CORCUTIS": "Amarela", "NATUREZAVINCULADA": "Roubo (art. 157)", "TIPOVINCULO": "V\u00a1tima", "RELACIONAMENTO": "", "PARENTESCO": "", "PLACA_VEICULO": "", "UF_VEICULO": "", "CIDADE_VEICULO": "", "DESCR_COR_VEICULO": "", "DESCR_MARCA_VEICULO": "", "ANO_FABRICACAO": "0", "ANO_MODELO": "0", "DESCR_TIPO_VEICULO": "", "QUANT_CELULAR": "", "MARCA_CELULAR": ""}, {"ANO_BO": "2019", "NUM_BO": "8904", "NUMERO_BOLETIM": "8904/2019", "BO_INICIADO": "20/04/2019 19:03", "BO_EMITIDO": "20/04/2019 21:07", "DATAOCORRENCIA": "20/04/2019", "PERIDOOCORRENCIA": "A TARDE", "DATACOMUNICACAO": "20/04/2019", "DATAELABORACAO": "20/04/2019 19:03", "BO_AUTORIA": "Desconhecida", "FLAGRANTE": "N\u00c6o", "NUMERO_BOLETIM_PRINCIPAL": "", "LOGRADOURO": "AVENIDA CAPIT\u00c7O SALOM\u00c7O", "NUMERO": "2340", "BAIRRO": "JD MOSTEIRO", "CIDADE": "RIBEIRAO PRETO", "UF": "SP", "LATITUDE": "-21,17253581", "LONGITUDE": "-47,79700138", "DESCRICAOLOCAL": "Com\u201arcio e servi\u2021os", "EXAME": "IC-IML", "SOLUCAO": "ENCAMINHAMENTO DP \u00b5REA DO FATO", "DELEGACIA_NOME": "CENTRAL POL.JUD-RIB. PRETO", "DELEGACIA_CIRCUNSCRICAO": "02\u00a7 D.P. RIBEIRAO PRETO", "ESPECIE": "T\u00a1tulo II - Patrim\u201cnio (arts. 155 a 183)", "RUBRICA": "Roubo (art. 157) - ESTABELECIMENTO COMERCIAL", "DESDOBRAMENTO": "\u00f53o. Se da viol\u02c6ncia resulta morte:", "STATUS": "Consumado", "NOMEPESSOA": "VAIL JULIAO", "TIPOPESSOA": "V\u00a1tima", "VITIMAFATAL": "Sim", "RG": "12800301", "RG_UF": "SP", "NATURALIDADE": "ITIRAPINA/SP", "NACIONALIDADE": "BRASILEIRA", "SEXO": "Masculino", "DATANASCIMENTO": "24/11/1958", "IDADE": "60", "ESTADOCIVIL": "Ignorado", "PROFISSAO": "FRENTISTA", "GRAUINSTRUCAO": "", "CORCUTIS": "Branca", "NATUREZAVINCULADA": "Roubo (art. 157)", "TIPOVINCULO": "V\u00a1tima", "RELACIONAMENTO": "", "PARENTESCO": "", "PLACA_VEICULO": "", "UF_VEICULO": "", "CIDADE_VEICULO": "", "DESCR_COR_VEICULO": "", "DESCR_MARCA_VEICULO": "", "ANO_FABRICACAO": "0", "ANO_MODELO": "0", "DESCR_TIPO_VEICULO": "", "QUANT_CELULAR": "", "MARCA_CELULAR": ""}, {"ANO_BO": "2019", "NUM_BO": "1723", "NUMERO_BOLETIM": "1723/2019", "BO_INICIADO": "20/04/2019 22:40", "BO_EMITIDO": "21/04/2019 00:17", "DATAOCORRENCIA": "20/04/2019", "PERIDOOCORRENCIA": "A NOITE", "DATACOMUNICACAO": "20/04/2019", "DATAELABORACAO": "20/04/2019 22:40", "BO_AUTORIA": "Desconhecida", "FLAGRANTE": "N\u00c6o", "NUMERO_BOLETIM_PRINCIPAL": "", "LOGRADOURO": "AVENIDA ANTONIO FREDERICO OZANAN", "NUMERO": "9100", "BAIRRO": "VILA HORTOL\u00b6NDIA", "CIDADE": "JUNDIAI", "UF": "SP", "LATITUDE": "-23,16677548", "LONGITUDE": "-46,91007404", "DESCRICAOLOCAL": "Via p\u00a3blica", "EXAME": "IC-IML", "SOLUCAO": "APRECIA\u20ac\u00c7O DO DELEGADO TITULAR", "DELEGACIA_NOME": "PLANT\u00c7O - 01\u00a7 D.P. JUNDIAI", "DELEGACIA_CIRCUNSCRICAO": "02\u00a7 D.P. JUNDIAI", "ESPECIE": "T\u00a1tulo II - Patrim\u201cnio (arts. 155 a 183)", "RUBRICA": "Roubo (art. 157) - TRANSEUNTE", "DESDOBRAMENTO": "\u00f53o. Se da viol\u02c6ncia resulta morte:", "STATUS": "Consumado", "NOMEPESSOA": "MARIO CEZAR PATELLI", "TIPOPESSOA": "V\u00a1tima", "VITIMAFATAL": "Sim", "RG": "40053611", "RG_UF": "SP", "NATURALIDADE": "JUNDIAI -SP", "NACIONALIDADE": "BRASILEIRA", "SEXO": "Masculino", "DATANASCIMENTO": "30/04/1987", "IDADE": "31", "ESTADOCIVIL": "Casado", "PROFISSAO": "AUTONOMO(A)", "GRAUINSTRUCAO": "2 Grau completo", "CORCUTIS": "Branca", "NATUREZAVINCULADA": "Roubo (art. 157)", "TIPOVINCULO": "V\u00a1tima", "RELACIONAMENTO": "", "PARENTESCO": "", "PLACA_VEICULO": "", "UF_VEICULO": "", "CIDADE_VEICULO": "", "DESCR_COR_VEICULO": "", "DESCR_MARCA_VEICULO": "", "ANO_FABRICACAO": "0", "ANO_MODELO": "0", "DESCR_TIPO_VEICULO": "", "QUANT_CELULAR": "", "MARCA_CELULAR": ""}, {"ANO_BO": "2019", "NUM_BO": "1139", "NUMERO_BOLETIM": "1139/2019", "BO_INICIADO": "20/04/2019 17:28", "BO_EMITIDO": "21/04/2019 01:20", "DATAOCORRENCIA": "20/04/2019", "PERIDOOCORRENCIA": "A TARDE", "DATACOMUNICACAO": "20/04/2019", "DATAELABORACAO": "20/04/2019 17:28", "BO_AUTORIA": "Conhecida", "FLAGRANTE": "Sim", "NUMERO_BOLETIM_PRINCIPAL": "", "LOGRADOURO": "PRA\u20acA STELIO MACHADO LOUREIRO", "NUMERO": "0", "BAIRRO": "CENTRO", "CIDADE": "TANABI", "UF": "SP", "LATITUDE": "-20,62395503", "LONGITUDE": "-49,65914894", "DESCRICAOLOCAL": "Via p\u00a3blica", "EXAME": "", "SOLUCAO": "APRECIA\u20ac\u00c7O DO DELEGADO TITULAR", "DELEGACIA_NOME": "DEL.POL.MIRASSOL", "DELEGACIA_CIRCUNSCRICAO": "DEL.POL.TANABI", "ESPECIE": "Ato infracional", "RUBRICA": "A.I.-Roubo (art. 157) - VEICULO", "DESDOBRAMENTO": "\u00f53o. Se da viol\u02c6ncia resulta morte", "STATUS": "Consumado", "NOMEPESSOA": "JOAO RONCOLATO", "TIPOPESSOA": "V\u00a1tima", "VITIMAFATAL": "Sim", "RG": "4255664", "RG_UF": "SP", "NATURALIDADE": "TANABI -SP", "NACIONALIDADE": "BRASILEIRA", "SEXO": "Masculino", "DATANASCIMENTO": "07/12/1934", "IDADE": "84", "ESTADOCIVIL": "Casado", "PROFISSAO": "MOTOTAXISTA", "GRAUINSTRUCAO": "", "CORCUTIS": "Branca", "NATUREZAVINCULADA": "A.I.-Roubo (art. 157)", "TIPOVINCULO": "V\u00a1tima", "RELACIONAMENTO": "", "PARENTESCO": "", "PLACA_VEICULO": "", "UF_VEICULO": "", "CIDADE_VEICULO": "", "DESCR_COR_VEICULO": "", "DESCR_MARCA_VEICULO": "", "ANO_FABRICACAO": "0", "ANO_MODELO": "0", "DESCR_TIPO_VEICULO": "", "QUANT_CELULAR": "", "MARCA_CELULAR": ""}, {"ANO_BO": "2019", "NUM_BO": "1139", "NUMERO_BOLETIM": "1139/2019", "BO_INICIADO": "20/04/2019 17:28", "BO_EMITIDO": "21/04/2019 01:20", "DATAOCORRENCIA": "20/04/2019", "PERIDOOCORRENCIA": "A TARDE", "DATACOMUNICACAO": "20/04/2019", "DATAELABORACAO": "20/04/2019 17:28", "BO_AUTORIA": "Conhecida", "FLAGRANTE": "Sim", "NUMERO_BOLETIM_PRINCIPAL": "", "LOGRADOURO": "PRA\u20acA STELIO MACHADO LOUREIRO", "NUMERO": "0", "BAIRRO": "CENTRO", "CIDADE": "TANABI", "UF": "SP", "LATITUDE": "-20,62395503", "LONGITUDE": "-49,65914894", "DESCRICAOLOCAL": "Via p\u00a3blica", "EXAME": "", "SOLUCAO": "APRECIA\u20ac\u00c7O DO DELEGADO TITULAR", "DELEGACIA_NOME": "DEL.POL.MIRASSOL", "DELEGACIA_CIRCUNSCRICAO": "DEL.POL.TANABI", "ESPECIE": "L 8069/90 - ECA", "RUBRICA": "Caput Corromper ou facilitar a corrup\u2021\u00c6o de menor de 18 anos (244B)", "DESDOBRAMENTO": "", "STATUS": "Consumado", "NOMEPESSOA": "JOAO RONCOLATO", "TIPOPESSOA": "V\u00a1tima", "VITIMAFATAL": "Sim", "RG": "4255664", "RG_UF": "SP", "NATURALIDADE": "TANABI -SP", "NACIONALIDADE": "BRASILEIRA", "SEXO": "Masculino", "DATANASCIMENTO": "07/12/1934", "IDADE": "84", "ESTADOCIVIL": "Casado", "PROFISSAO": "MOTOTAXISTA", "GRAUINSTRUCAO": "", "CORCUTIS": "Branca", "NATUREZAVINCULADA": "Caput Corromper ou facilitar a corrup\u2021\u00c6o de menor de 18 anos (244B)", "TIPOVINCULO": "V\u00a1tima", "RELACIONAMENTO": "", "PARENTESCO": "", "PLACA_VEICULO": "EXO6060", "UF_VEICULO": "SP", "CIDADE_VEICULO": "TANABI", "DESCR_COR_VEICULO": "Cinza", "DESCR_MARCA_VEICULO": "VW/VOYAGE 1.6L MB5", "ANO_FABRICACAO": "2019", "ANO_MODELO": "2019", "DESCR_TIPO_VEICULO": "AUTOMOVEL", "QUANT_CELULAR": "", "MARCA_CELULAR": ""}, {"ANO_BO": "2019", "NUM_BO": "1139", "NUMERO_BOLETIM": "1139/2019", "BO_INICIADO": "20/04/2019 17:28", "BO_EMITIDO": "21/04/2019 01:20", "DATAOCORRENCIA": "20/04/2019", "PERIDOOCORRENCIA": "A TARDE", "DATACOMUNICACAO": "20/04/2019", "DATAELABORACAO": "20/04/2019 17:28", "BO_AUTORIA": "Conhecida", "FLAGRANTE": "Sim", "NUMERO_BOLETIM_PRINCIPAL": "", "LOGRADOURO": "PRA\u20acA STELIO MACHADO LOUREIRO", "NUMERO": "0", "BAIRRO": "CENTRO", "CIDADE": "TANABI", "UF": "SP", "LATITUDE": "-20,62395503", "LONGITUDE": "-49,65914894", "DESCRICAOLOCAL": "Via p\u00a3blica", "EXAME": "", "SOLUCAO": "APRECIA\u20ac\u00c7O DO DELEGADO TITULAR", "DELEGACIA_NOME": "DEL.POL.MIRASSOL", "DELEGACIA_CIRCUNSCRICAO": "DEL.POL.TANABI", "ESPECIE": "T\u00a1tulo II - Patrim\u201cnio (arts. 155 a 183)", "RUBRICA": "Roubo (art. 157) - VEICULO", "DESDOBRAMENTO": "\u00f53o. Se da viol\u02c6ncia resulta morte:", "STATUS": "Consumado", "NOMEPESSOA": "JOAO RONCOLATO", "TIPOPESSOA": "V\u00a1tima", "VITIMAFATAL": "Sim", "RG": "4255664", "RG_UF": "SP", "NATURALIDADE": "TANABI -SP", "NACIONALIDADE": "BRASILEIRA", "SEXO": "Masculino", "DATANASCIMENTO": "07/12/1934", "IDADE": "84", "ESTADOCIVIL": "Casado", "PROFISSAO": "MOTOTAXISTA", "GRAUINSTRUCAO": "", "CORCUTIS": "Branca", "NATUREZAVINCULADA": "Roubo (art. 157)", "TIPOVINCULO": "V\u00a1tima", "RELACIONAMENTO": "", "PARENTESCO": "", "PLACA_VEICULO": "EXO6060", "UF_VEICULO": "SP", "CIDADE_VEICULO": "TANABI", "DESCR_COR_VEICULO": "Cinza", "DESCR_MARCA_VEICULO": "VW/VOYAGE 1.6L MB5", "ANO_FABRICACAO": "2019", "ANO_MODELO": "2019", "DESCR_TIPO_VEICULO": "AUTOMOVEL", "QUANT_CELULAR": "", "MARCA_CELULAR": ""}, {"ANO_BO": "2019", "NUM_BO": "1139", "NUMERO_BOLETIM": "1139/2019", "BO_INICIADO": "20/04/2019 17:28", "BO_EMITIDO": "21/04/2019 01:20", "DATAOCORRENCIA": "20/04/2019", "PERIDOOCORRENCIA": "A TARDE", "DATACOMUNICACAO": "20/04/2019", "DATAELABORACAO": "20/04/2019 17:28", "BO_AUTORIA": "Conhecida", "FLAGRANTE": "Sim", "NUMERO_BOLETIM_PRINCIPAL": "", "LOGRADOURO": "PRA\u20acA STELIO MACHADO LOUREIRO", "NUMERO": "0", "BAIRRO": "CENTRO", "CIDADE": "TANABI", "UF": "SP", "LATITUDE": "-20,62395503", "LONGITUDE": "-49,65914894", "DESCRICAOLOCAL": "Via p\u00a3blica", "EXAME": "", "SOLUCAO": "APRECIA\u20ac\u00c7O DO DELEGADO TITULAR", "DELEGACIA_NOME": "DEL.POL.MIRASSOL", "DELEGACIA_CIRCUNSCRICAO": "DEL.POL.TANABI", "ESPECIE": "Ato infracional", "RUBRICA": "A.I.-Roubo (art. 157) - VEICULO", "DESDOBRAMENTO": "\u00f53o. Se da viol\u02c6ncia resulta morte", "STATUS": "Consumado", "NOMEPESSOA": "JOAO RONCOLATO", "TIPOPESSOA": "V\u00a1tima", "VITIMAFATAL": "Sim", "RG": "4255664", "RG_UF": "SP", "NATURALIDADE": "TANABI -SP", "NACIONALIDADE": "BRASILEIRA", "SEXO": "Masculino", "DATANASCIMENTO": "07/12/1934", "IDADE": "84", "ESTADOCIVIL": "Casado", "PROFISSAO": "MOTOTAXISTA", "GRAUINSTRUCAO": "", "CORCUTIS": "Branca", "NATUREZAVINCULADA": "A.I.-Roubo (art. 157)", "TIPOVINCULO": "V\u00a1tima", "RELACIONAMENTO": "", "PARENTESCO": "", "PLACA_VEICULO": "EXO6060", "UF_VEICULO": "SP", "CIDADE_VEICULO": "TANABI", "DESCR_COR_VEICULO": "Cinza", "DESCR_MARCA_VEICULO": "VW/VOYAGE 1.6L MB5", "ANO_FABRICACAO": "2019", "ANO_MODELO": "2019", "DESCR_TIPO_VEICULO": "AUTOMOVEL", "QUANT_CELULAR": "", "MARCA_CELULAR": ""}, {"ANO_BO": "2019", "NUM_BO": "1139", "NUMERO_BOLETIM": "1139/2019", "BO_INICIADO": "20/04/2019 17:28", "BO_EMITIDO": "21/04/2019 01:20", "DATAOCORRENCIA": "20/04/2019", "PERIDOOCORRENCIA": "A TARDE", "DATACOMUNICACAO": "20/04/2019", "DATAELABORACAO": "20/04/2019 17:28", "BO_AUTORIA": "Conhecida", "FLAGRANTE": "Sim", "NUMERO_BOLETIM_PRINCIPAL": "", "LOGRADOURO": "PRA\u20acA STELIO MACHADO LOUREIRO", "NUMERO": "0", "BAIRRO": "CENTRO", "CIDADE": "TANABI", "UF": "SP", "LATITUDE": "-20,62395503", "LONGITUDE": "-49,65914894", "DESCRICAOLOCAL": "Via p\u00a3blica", "EXAME": "", "SOLUCAO": "APRECIA\u20ac\u00c7O DO DELEGADO TITULAR", "DELEGACIA_NOME": "DEL.POL.MIRASSOL", "DELEGACIA_CIRCUNSCRICAO": "DEL.POL.TANABI", "ESPECIE": "T\u00a1tulo II - Patrim\u201cnio (arts. 155 a 183)", "RUBRICA": "Roubo (art. 157) - VEICULO", "DESDOBRAMENTO": "\u00f53o. Se da viol\u02c6ncia resulta morte:", "STATUS": "Consumado", "NOMEPESSOA": "JOAO RONCOLATO", "TIPOPESSOA": "V\u00a1tima", "VITIMAFATAL": "Sim", "RG": "4255664", "RG_UF": "SP", "NATURALIDADE": "TANABI -SP", "NACIONALIDADE": "BRASILEIRA", "SEXO": "Masculino", "DATANASCIMENTO": "07/12/1934", "IDADE": "84", "ESTADOCIVIL": "Casado", "PROFISSAO": "MOTOTAXISTA", "GRAUINSTRUCAO": "", "CORCUTIS": "Branca", "NATUREZAVINCULADA": "Roubo (art. 157)", "TIPOVINCULO": "V\u00a1tima", "RELACIONAMENTO": "", "PARENTESCO": "", "PLACA_VEICULO": "", "UF_VEICULO": "", "CIDADE_VEICULO": "", "DESCR_COR_VEICULO": "", "DESCR_MARCA_VEICULO": "", "ANO_FABRICACAO": "0", "ANO_MODELO": "0", "DESCR_TIPO_VEICULO": "", "QUANT_CELULAR": "", "MARCA_CELULAR": ""}, {"ANO_BO": "2019", "NUM_BO": "1139", "NUMERO_BOLETIM": "1139/2019", "BO_INICIADO": "20/04/2019 17:28", "BO_EMITIDO": "21/04/2019 01:20", "DATAOCORRENCIA": "20/04/2019", "PERIDOOCORRENCIA": "A TARDE", "DATACOMUNICACAO": "20/04/2019", "DATAELABORACAO": "20/04/2019 17:28", "BO_AUTORIA": "Conhecida", "FLAGRANTE": "Sim", "NUMERO_BOLETIM_PRINCIPAL": "", "LOGRADOURO": "PRA\u20acA STELIO MACHADO LOUREIRO", "NUMERO": "0", "BAIRRO": "CENTRO", "CIDADE": "TANABI", "UF": "SP", "LATITUDE": "-20,62395503", "LONGITUDE": "-49,65914894", "DESCRICAOLOCAL": "Via p\u00a3blica", "EXAME": "", "SOLUCAO": "APRECIA\u20ac\u00c7O DO DELEGADO TITULAR", "DELEGACIA_NOME": "DEL.POL.MIRASSOL", "DELEGACIA_CIRCUNSCRICAO": "DEL.POL.TANABI", "ESPECIE": "L 8069/90 - ECA", "RUBRICA": "Caput Corromper ou facilitar a corrup\u2021\u00c6o de menor de 18 anos (244B)", "DESDOBRAMENTO": "", "STATUS": "Consumado", "NOMEPESSOA": "JOAO RONCOLATO", "TIPOPESSOA": "V\u00a1tima", "VITIMAFATAL": "Sim", "RG": "4255664", "RG_UF": "SP", "NATURALIDADE": "TANABI -SP", "NACIONALIDADE": "BRASILEIRA", "SEXO": "Masculino", "DATANASCIMENTO": "07/12/1934", "IDADE": "84", "ESTADOCIVIL": "Casado", "PROFISSAO": "MOTOTAXISTA", "GRAUINSTRUCAO": "", "CORCUTIS": "Branca", "NATUREZAVINCULADA": "Caput Corromper ou facilitar a corrup\u2021\u00c6o de menor de 18 anos (244B)", "TIPOVINCULO": "V\u00a1tima", "RELACIONAMENTO": "", "PARENTESCO": "", "PLACA_VEICULO": "", "UF_VEICULO": "", "CIDADE_VEICULO": "", "DESCR_COR_VEICULO": "", "DESCR_MARCA_VEICULO": "", "ANO_FABRICACAO": "0", "ANO_MODELO": "0", "DESCR_TIPO_VEICULO": "", "QUANT_CELULAR": "", "MARCA_CELULAR": ""}, {"ANO_BO": "2019", "NUM_BO": "180", "NUMERO_BOLETIM": "180/2019", "BO_INICIADO": "22/04/2019 11:24", "BO_EMITIDO": "22/04/2019 11:42", "DATAOCORRENCIA": "20/04/2019", "PERIDOOCORRENCIA": "A TARDE", "DATACOMUNICACAO": "22/04/2019", "DATAELABORACAO": "22/04/2019 11:24", "BO_AUTORIA": "Desconhecida", "FLAGRANTE": "N\u00c6o", "NUMERO_BOLETIM_PRINCIPAL": "8904/2019 - 100919", "LOGRADOURO": "AVENIDA CAPIT\u00c7O SALOM\u00c7O", "NUMERO": "2340", "BAIRRO": "JD MOSTEIRO", "CIDADE": "RIBEIRAO PRETO", "UF": "SP", "LATITUDE": "-21,17253581", "LONGITUDE": "-47,79700138", "DESCRICAOLOCAL": "Com\u201arcio e servi\u2021os", "EXAME": "IC-IML", "SOLUCAO": "BO PARA ADENDO", "DELEGACIA_NOME": "DEL.INV.GER. RIBEIRAO PRETO", "DELEGACIA_CIRCUNSCRICAO": "02\u00a7 D.P. RIBEIRAO PRETO", "ESPECIE": "Localiza\u2021\u00c6o e/ou Devolu\u2021\u00c6o", "RUBRICA": "Localiza\u2021\u00c6o/Apreens\u00c6o de objeto", "DESDOBRAMENTO": "", "STATUS": "Consumado", "NOMEPESSOA": "", "TIPOPESSOA": "", "VITIMAFATAL": "", "RG": "", "RG_UF": "", "NATURALIDADE": "", "NACIONALIDADE": "", "SEXO": "", "DATANASCIMENTO": "", "IDADE": "", "ESTADOCIVIL": "", "PROFISSAO": "", "GRAUINSTRUCAO": "", "CORCUTIS": "", "NATUREZAVINCULADA": "", "TIPOVINCULO": "", "RELACIONAMENTO": "", "PARENTESCO": "", "PLACA_VEICULO": "", "UF_VEICULO": "", "CIDADE_VEICULO": "", "DESCR_COR_VEICULO": "", "DESCR_MARCA_VEICULO": "", "ANO_FABRICACAO": "0", "ANO_MODELO": "0", "DESCR_TIPO_VEICULO": "", "QUANT_CELULAR": "", "MARCA_CELULAR": ""}, {"ANO_BO": "2019", "NUM_BO": "180", "NUMERO_BOLETIM": "180/2019", "BO_INICIADO": "22/04/2019 11:24", "BO_EMITIDO": "22/04/2019 11:42", "DATAOCORRENCIA": "20/04/2019", "PERIDOOCORRENCIA": "A TARDE", "DATACOMUNICACAO": "22/04/2019", "DATAELABORACAO": "22/04/2019 11:24", "BO_AUTORIA": "Desconhecida", "FLAGRANTE": "N\u00c6o", "NUMERO_BOLETIM_PRINCIPAL": "8904/2019 - 100919", "LOGRADOURO": "AVENIDA CAPIT\u00c7O SALOM\u00c7O", "NUMERO": "2340", "BAIRRO": "JD MOSTEIRO", "CIDADE": "RIBEIRAO PRETO", "UF": "SP", "LATITUDE": "-21,17253581", "LONGITUDE": "-47,79700138", "DESCRICAOLOCAL": "Com\u201arcio e servi\u2021os", "EXAME": "IC-IML", "SOLUCAO": "BO PARA ADENDO", "DELEGACIA_NOME": "DEL.INV.GER. RIBEIRAO PRETO", "DELEGACIA_CIRCUNSCRICAO": "02\u00a7 D.P. RIBEIRAO PRETO", "ESPECIE": "T\u00a1tulo II - Patrim\u201cnio (arts. 155 a 183)", "RUBRICA": "Roubo (art. 157) - ESTABELECIMENTO COMERCIAL", "DESDOBRAMENTO": "\u00f53o. Se da viol\u02c6ncia resulta morte:", "STATUS": "Consumado", "NOMEPESSOA": "VAIL JULIAO", "TIPOPESSOA": "V\u00a1tima", "VITIMAFATAL": "Sim", "RG": "12800301", "RG_UF": "SP", "NATURALIDADE": "ITIRAPINA/SP", "NACIONALIDADE": "BRASILEIRA", "SEXO": "Masculino", "DATANASCIMENTO": "24/11/1958", "IDADE": "60", "ESTADOCIVIL": "Ignorado", "PROFISSAO": "FRENTISTA", "GRAUINSTRUCAO": "", "CORCUTIS": "Branca", "NATUREZAVINCULADA": "Roubo (art. 157)", "TIPOVINCULO": "V\u00a1tima", "RELACIONAMENTO": "", "PARENTESCO": "", "PLACA_VEICULO": "", "UF_VEICULO": "", "CIDADE_VEICULO": "", "DESCR_COR_VEICULO": "", "DESCR_MARCA_VEICULO": "", "ANO_FABRICACAO": "0", "ANO_MODELO": "0", "DESCR_TIPO_VEICULO": "", "QUANT_CELULAR": "", "MARCA_CELULAR": ""}, {"ANO_BO": "2019", "NUM_BO": "112", "NUMERO_BOLETIM": "112/2019", "BO_INICIADO": "23/04/2019 16:41", "BO_EMITIDO": "23/04/2019 16:55", "DATAOCORRENCIA": "20/04/2019", "PERIDOOCORRENCIA": "EM HORA INCERTA", "DATACOMUNICACAO": "23/04/2019", "DATAELABORACAO": "23/04/2019 16:41", "BO_AUTORIA": "Desconhecida", "FLAGRANTE": "N\u00c6o", "NUMERO_BOLETIM_PRINCIPAL": "111/2019 - 80508", "LOGRADOURO": "", "NUMERO": "0", "BAIRRO": "AREA RURAL", "CIDADE": "PARAGUACU PAULISTA", "UF": "SP", "LATITUDE": "", "LONGITUDE": "", "DESCRICAOLOCAL": "Resid\u02c6ncia", "EXAME": "IC-IML", "SOLUCAO": "BO PARA ADENDO", "DELEGACIA_NOME": "DEL.POL.PLANT\u00c7O PARAGUA\u20acU PTA", "DELEGACIA_CIRCUNSCRICAO": "DEL.POL.PLANT\u00c7O PARAGUA\u20acU PTA", "ESPECIE": "T\u00a1tulo II - Patrim\u201cnio (arts. 155 a 183)", "RUBRICA": "Roubo (art. 157) - OUTROS", "DESDOBRAMENTO": "\u00f53o. Se da viol\u02c6ncia resulta morte:", "STATUS": "Consumado", "NOMEPESSOA": "CARLOS ANTONIO BELLO", "TIPOPESSOA": "V\u00a1tima", "VITIMAFATAL": "Sim", "RG": "28896738", "RG_UF": "SP", "NATURALIDADE": "PARAGUA\u20acU PAULISTA SP", "NACIONALIDADE": "BRASILEIRA", "SEXO": "Masculino", "DATANASCIMENTO": "02/09/1955", "IDADE": "63", "ESTADOCIVIL": "Uni\u00c6o Est\u00a0vel", "PROFISSAO": "APOSENTADO(A)", "GRAUINSTRUCAO": "1 Grau incompleto", "CORCUTIS": "Branca", "NATUREZAVINCULADA": "Roubo (art. 157)", "TIPOVINCULO": "V\u00a1tima", "RELACIONAMENTO": "", "PARENTESCO": "", "PLACA_VEICULO": "", "UF_VEICULO": "", "CIDADE_VEICULO": "", "DESCR_COR_VEICULO": "", "DESCR_MARCA_VEICULO": "", "ANO_FABRICACAO": "0", "ANO_MODELO": "0", "DESCR_TIPO_VEICULO": "", "QUANT_CELULAR": "", "MARCA_CELULAR": ""}, {"ANO_BO": "2019", "NUM_BO": "2175", "NUMERO_BOLETIM": "2175/2019", "BO_INICIADO": "24/04/2019 22:18", "BO_EMITIDO": "25/04/2019 04:07", "DATAOCORRENCIA": "24/04/2019", "PERIDOOCORRENCIA": "A NOITE", "DATACOMUNICACAO": "24/04/2019", "DATAELABORACAO": "24/04/2019 22:18", "BO_AUTORIA": "Desconhecida", "FLAGRANTE": "N\u00c6o", "NUMERO_BOLETIM_PRINCIPAL": "", "LOGRADOURO": "", "NUMERO": "0", "BAIRRO": "PQ VITORIA", "CIDADE": "FRANCO DA ROCHA", "UF": "SP", "LATITUDE": "", "LONGITUDE": "", "DESCRICAOLOCAL": "Resid\u02c6ncia", "EXAME": "IC-IML", "SOLUCAO": "APRECIA\u20ac\u00c7O DO DELEGADO TITULAR", "DELEGACIA_NOME": "DEL.POL.FRANCO ROCHA", "DELEGACIA_CIRCUNSCRICAO": "DEL.POL.FRANCO ROCHA", "ESPECIE": "T\u00a1tulo II - Patrim\u201cnio (arts. 155 a 183)", "RUBRICA": "Roubo (art. 157) - RESIDENCIA", "DESDOBRAMENTO": "\u00f53o. Se da viol\u02c6ncia resulta morte:", "STATUS": "Consumado", "NOMEPESSOA": "APARECIDA REGINA VIEIRA DA TRINDADE", "TIPOPESSOA": "V\u00a1tima", "VITIMAFATAL": "Sim", "RG": "20856179", "RG_UF": "SP", "NATURALIDADE": "S.PAULO -SP", "NACIONALIDADE": "BRASILEIRA", "SEXO": "Feminino", "DATANASCIMENTO": "15/09/1966", "IDADE": "52", "ESTADOCIVIL": "", "PROFISSAO": "", "GRAUINSTRUCAO": "", "CORCUTIS": "Branca", "NATUREZAVINCULADA": "Roubo (art. 157)", "TIPOVINCULO": "V\u00a1tima", "RELACIONAMENTO": "", "PARENTESCO": "", "PLACA_VEICULO": "", "UF_VEICULO": "", "CIDADE_VEICULO": "", "DESCR_COR_VEICULO": "", "DESCR_MARCA_VEICULO": "", "ANO_FABRICACAO": "0", "ANO_MODELO": "0", "DESCR_TIPO_VEICULO": "", "QUANT_CELULAR": "", "MARCA_CELULAR": ""}, {"ANO_BO": "2019", "NUM_BO": "555", "NUMERO_BOLETIM": "555/2019", "BO_INICIADO": "26/04/2019 16:26", "BO_EMITIDO": "26/04/2019 16:33", "DATAOCORRENCIA": "16/04/2019", "PERIDOOCORRENCIA": "A NOITE", "DATACOMUNICACAO": "26/04/2019", "DATAELABORACAO": "26/04/2019 16:26", "BO_AUTORIA": "Desconhecida", "FLAGRANTE": "N\u00c6o", "NUMERO_BOLETIM_PRINCIPAL": "1806/2019 - 130516", "LOGRADOURO": "RUA SANTA PAULA", "NUMERO": "428", "BAIRRO": "CENTRO", "CIDADE": "TREMEMBE", "UF": "SP", "LATITUDE": "-22,9589822", "LONGITUDE": "-45,55004741", "DESCRICAOLOCAL": "Sa\u00a3de", "EXAME": "", "SOLUCAO": "BO PARA ADENDO", "DELEGACIA_NOME": "DEL.POL.TREMEMBE", "DELEGACIA_CIRCUNSCRICAO": "DEL.POL.TREMEMBE", "ESPECIE": "T\u00a1tulo II - Patrim\u201cnio (arts. 155 a 183)", "RUBRICA": "Roubo (art. 157) - TRANSEUNTE", "DESDOBRAMENTO": "\u00f53o. Se da viol\u02c6ncia resulta morte:", "STATUS": "Consumado", "NOMEPESSOA": "ROSEMAR ORTIZ BARBOSA", "TIPOPESSOA": "V\u00a1tima", "VITIMAFATAL": "Sim", "RG": "25584965", "RG_UF": "SP", "NATURALIDADE": "LORENA -SP", "NACIONALIDADE": "BRASILEIRA", "SEXO": "Masculino", "DATANASCIMENTO": "14/06/1971", "IDADE": "47", "ESTADOCIVIL": "Uni\u00c6o Est\u00a0vel", "PROFISSAO": "AJUDANTE DE PEDREIRO", "GRAUINSTRUCAO": "", "CORCUTIS": "Branca", "NATUREZAVINCULADA": "Roubo (art. 157)", "TIPOVINCULO": "V\u00a1tima", "RELACIONAMENTO": "", "PARENTESCO": "", "PLACA_VEICULO": "", "UF_VEICULO": "", "CIDADE_VEICULO": "", "DESCR_COR_VEICULO": "", "DESCR_MARCA_VEICULO": "", "ANO_FABRICACAO": "0", "ANO_MODELO": "0", "DESCR_TIPO_VEICULO": "", "QUANT_CELULAR": "", "MARCA_CELULAR": ""}, {"ANO_BO": "2019", "NUM_BO": "1228", "NUMERO_BOLETIM": "1228/2019", "BO_INICIADO": "29/04/2019 00:47", "BO_EMITIDO": "29/04/2019 02:25", "DATAOCORRENCIA": "28/04/2019", "PERIDOOCORRENCIA": "A NOITE", "DATACOMUNICACAO": "29/04/2019", "DATAELABORACAO": "29/04/2019 00:47", "BO_AUTORIA": "Conhecida", "FLAGRANTE": "Sim", "NUMERO_BOLETIM_PRINCIPAL": "", "LOGRADOURO": "RUA HILDEBRANDO SIQUEIRA", "NUMERO": "562", "BAIRRO": "JABAQUARA", "CIDADE": "S.PAULO", "UF": "SP", "LATITUDE": "-23,6614373", "LONGITUDE": "-46,63943884", "DESCRICAOLOCAL": "Via p\u00a3blica", "EXAME": "IML", "SOLUCAO": "BO PARA FLAGRANTE", "DELEGACIA_NOME": "95\u00a7 D.P. HELI\u00e0POLIS", "DELEGACIA_CIRCUNSCRICAO": "97\u00a7 D.P. AMERICANOPOLIS", "ESPECIE": "T\u00a1tulo II - Patrim\u201cnio (arts. 155 a 183)", "RUBRICA": "Roubo (art. 157) - TRANSEUNTE", "DESDOBRAMENTO": "\u00f53o. Se da viol\u02c6ncia resulta morte:", "STATUS": "Consumado", "NOMEPESSOA": "JOAO BATISTA GABRIEL", "TIPOPESSOA": "V\u00a1tima", "VITIMAFATAL": "Sim", "RG": "9019186", "RG_UF": "SP", "NATURALIDADE": "MERUOCA -CE", "NACIONALIDADE": "", "SEXO": "Masculino", "DATANASCIMENTO": "14/02/1953", "IDADE": "66", "ESTADOCIVIL": "Ignorado", "PROFISSAO": "", "GRAUINSTRUCAO": "", "CORCUTIS": "Branca", "NATUREZAVINCULADA": "Roubo (art. 157)", "TIPOVINCULO": "V\u00a1tima", "RELACIONAMENTO": "", "PARENTESCO": "", "PLACA_VEICULO": "", "UF_VEICULO": "", "CIDADE_VEICULO": "", "DESCR_COR_VEICULO": "", "DESCR_MARCA_VEICULO": "", "ANO_FABRICACAO": "0", "ANO_MODELO": "0", "DESCR_TIPO_VEICULO": "", "QUANT_CELULAR": "", "MARCA_CELULAR": ""}, {"ANO_BO": "2019", "NUM_BO": "198", "NUMERO_BOLETIM": "198/2019", "BO_INICIADO": "29/04/2019 15:50", "BO_EMITIDO": "29/04/2019 16:14", "DATAOCORRENCIA": "20/04/2019", "PERIDOOCORRENCIA": "A TARDE", "DATACOMUNICACAO": "29/04/2019", "DATAELABORACAO": "29/04/2019 15:50", "BO_AUTORIA": "Conhecida", "FLAGRANTE": "N\u00c6o", "NUMERO_BOLETIM_PRINCIPAL": "180/2019 - 100001", "LOGRADOURO": "AVENIDA CAPIT\u00c7O SALOM\u00c7O", "NUMERO": "2340", "BAIRRO": "JD MOSTEIRO", "CIDADE": "RIBEIRAO PRETO", "UF": "SP", "LATITUDE": "-21,17253581", "LONGITUDE": "-47,79700138", "DESCRICAOLOCAL": "Com\u201arcio e servi\u2021os", "EXAME": "IC-IML", "SOLUCAO": "BO PARA ADENDO", "DELEGACIA_NOME": "DEL.INV.GER. RIBEIRAO PRETO", "DELEGACIA_CIRCUNSCRICAO": "02\u00a7 D.P. RIBEIRAO PRETO", "ESPECIE": "Ato infracional", "RUBRICA": "A.I.-Roubo (art. 157) - ESTABELECIMENTO COMERCIAL", "DESDOBRAMENTO": "\u00f53o. Se da viol\u02c6ncia resulta morte", "STATUS": "Consumado", "NOMEPESSOA": "VAIL JULIAO", "TIPOPESSOA": "V\u00a1tima", "VITIMAFATAL": "Sim", "RG": "12800301", "RG_UF": "SP", "NATURALIDADE": "ITIRAPINA/SP", "NACIONALIDADE": "BRASILEIRA", "SEXO": "Masculino", "DATANASCIMENTO": "24/11/1958", "IDADE": "60", "ESTADOCIVIL": "Ignorado", "PROFISSAO": "FRENTISTA", "GRAUINSTRUCAO": "", "CORCUTIS": "Branca", "NATUREZAVINCULADA": "A.I.-Roubo (art. 157)", "TIPOVINCULO": "V\u00a1tima", "RELACIONAMENTO": "", "PARENTESCO": "", "PLACA_VEICULO": "", "UF_VEICULO": "", "CIDADE_VEICULO": "", "DESCR_COR_VEICULO": "", "DESCR_MARCA_VEICULO": "", "ANO_FABRICACAO": "0", "ANO_MODELO": "0", "DESCR_TIPO_VEICULO": "", "QUANT_CELULAR": "", "MARCA_CELULAR": ""}, {"ANO_BO": "2019", "NUM_BO": "198", "NUMERO_BOLETIM": "198/2019", "BO_INICIADO": "29/04/2019 15:50", "BO_EMITIDO": "29/04/2019 16:14", "DATAOCORRENCIA": "20/04/2019", "PERIDOOCORRENCIA": "A TARDE", "DATACOMUNICACAO": "29/04/2019", "DATAELABORACAO": "29/04/2019 15:50", "BO_AUTORIA": "Conhecida", "FLAGRANTE": "N\u00c6o", "NUMERO_BOLETIM_PRINCIPAL": "180/2019 - 100001", "LOGRADOURO": "AVENIDA CAPIT\u00c7O SALOM\u00c7O", "NUMERO": "2340", "BAIRRO": "JD MOSTEIRO", "CIDADE": "RIBEIRAO PRETO", "UF": "SP", "LATITUDE": "-21,17253581", "LONGITUDE": "-47,79700138", "DESCRICAOLOCAL": "Com\u201arcio e servi\u2021os", "EXAME": "IC-IML", "SOLUCAO": "BO PARA ADENDO", "DELEGACIA_NOME": "DEL.INV.GER. RIBEIRAO PRETO", "DELEGACIA_CIRCUNSCRICAO": "02\u00a7 D.P. RIBEIRAO PRETO", "ESPECIE": "T\u00a1tulo II - Patrim\u201cnio (arts. 155 a 183)", "RUBRICA": "Roubo (art. 157) - ESTABELECIMENTO COMERCIAL", "DESDOBRAMENTO": "\u00f53o. Se da viol\u02c6ncia resulta morte:", "STATUS": "Consumado", "NOMEPESSOA": "VAIL JULIAO", "TIPOPESSOA": "V\u00a1tima", "VITIMAFATAL": "Sim", "RG": "12800301", "RG_UF": "SP", "NATURALIDADE": "ITIRAPINA/SP", "NACIONALIDADE": "BRASILEIRA", "SEXO": "Masculino", "DATANASCIMENTO": "24/11/1958", "IDADE": "60", "ESTADOCIVIL": "Ignorado", "PROFISSAO": "FRENTISTA", "GRAUINSTRUCAO": "", "CORCUTIS": "Branca", "NATUREZAVINCULADA": "Roubo (art. 157)", "TIPOVINCULO": "V\u00a1tima", "RELACIONAMENTO": "", "PARENTESCO": "", "PLACA_VEICULO": "", "UF_VEICULO": "", "CIDADE_VEICULO": "", "DESCR_COR_VEICULO": "", "DESCR_MARCA_VEICULO": "", "ANO_FABRICACAO": "0", "ANO_MODELO": "0", "DESCR_TIPO_VEICULO": "", "QUANT_CELULAR": "", "MARCA_CELULAR": ""}, {"ANO_BO": "2019", "NUM_BO": "198", "NUMERO_BOLETIM": "198/2019", "BO_INICIADO": "29/04/2019 15:50", "BO_EMITIDO": "29/04/2019 16:14", "DATAOCORRENCIA": "20/04/2019", "PERIDOOCORRENCIA": "A TARDE", "DATACOMUNICACAO": "29/04/2019", "DATAELABORACAO": "29/04/2019 15:50", "BO_AUTORIA": "Conhecida", "FLAGRANTE": "N\u00c6o", "NUMERO_BOLETIM_PRINCIPAL": "180/2019 - 100001", "LOGRADOURO": "AVENIDA CAPIT\u00c7O SALOM\u00c7O", "NUMERO": "2340", "BAIRRO": "JD MOSTEIRO", "CIDADE": "RIBEIRAO PRETO", "UF": "SP", "LATITUDE": "-21,17253581", "LONGITUDE": "-47,79700138", "DESCRICAOLOCAL": "Com\u201arcio e servi\u2021os", "EXAME": "IC-IML", "SOLUCAO": "BO PARA ADENDO", "DELEGACIA_NOME": "DEL.INV.GER. RIBEIRAO PRETO", "DELEGACIA_CIRCUNSCRICAO": "02\u00a7 D.P. RIBEIRAO PRETO", "ESPECIE": "Localiza\u2021\u00c6o e/ou Devolu\u2021\u00c6o", "RUBRICA": "Localiza\u2021\u00c6o/Apreens\u00c6o de objeto", "DESDOBRAMENTO": "", "STATUS": "Consumado", "NOMEPESSOA": "", "TIPOPESSOA": "", "VITIMAFATAL": "", "RG": "", "RG_UF": "", "NATURALIDADE": "", "NACIONALIDADE": "", "SEXO": "", "DATANASCIMENTO": "", "IDADE": "", "ESTADOCIVIL": "", "PROFISSAO": "", "GRAUINSTRUCAO": "", "CORCUTIS": "", "NATUREZAVINCULADA": "", "TIPOVINCULO": "", "RELACIONAMENTO": "", "PARENTESCO": "", "PLACA_VEICULO": "", "UF_VEICULO": "", "CIDADE_VEICULO": "", "DESCR_COR_VEICULO": "", "DESCR_MARCA_VEICULO": "", "ANO_FABRICACAO": "0", "ANO_MODELO": "0", "DESCR_TIPO_VEICULO": "", "QUANT_CELULAR": "", "MARCA_CELULAR": ""}]